odoo/addons/account_vendor_bank_account_default/README.rst
odoo/addons/account_vendor_bank_account_default/__init__.py
odoo/addons/account_vendor_bank_account_default/__manifest__.py
odoo/addons/account_vendor_bank_account_default/i18n/account_vendor_bank_account_default.pot
odoo/addons/account_vendor_bank_account_default/i18n/ca.po
odoo/addons/account_vendor_bank_account_default/i18n/es.po
odoo/addons/account_vendor_bank_account_default/i18n/it.po
odoo/addons/account_vendor_bank_account_default/models/__init__.py
odoo/addons/account_vendor_bank_account_default/models/account_move.py
odoo/addons/account_vendor_bank_account_default/models/res_partner.py
odoo/addons/account_vendor_bank_account_default/readme/CONFIGURE.md
odoo/addons/account_vendor_bank_account_default/readme/CONTRIBUTORS.md
odoo/addons/account_vendor_bank_account_default/readme/DESCRIPTION.md
odoo/addons/account_vendor_bank_account_default/readme/ROADMAP.md
odoo/addons/account_vendor_bank_account_default/readme/USAGE.md
odoo/addons/account_vendor_bank_account_default/static/description/icon.png
odoo/addons/account_vendor_bank_account_default/static/description/icon.svg
odoo/addons/account_vendor_bank_account_default/static/description/index.html
odoo/addons/account_vendor_bank_account_default/tests/__init__.py
odoo/addons/account_vendor_bank_account_default/tests/test_account_vendor_bank_account_default.py
odoo/addons/account_vendor_bank_account_default/views/res_partner_views.xml
odoo_addon_account_vendor_bank_account_default-18.0.1.0.0.2.dist-info/METADATA
odoo_addon_account_vendor_bank_account_default-18.0.1.0.0.2.dist-info/WHEEL
odoo_addon_account_vendor_bank_account_default-18.0.1.0.0.2.dist-info/top_level.txt
odoo_addon_account_vendor_bank_account_default-18.0.1.0.0.2.dist-info/RECORD
